ASTRA/__init__.py
ASTRA/Components/Modelling.py
ASTRA/Components/Spectral_Normalization.py
ASTRA/Components/SpectrumComponent.py
ASTRA/Components/__init__.py
ASTRA/DataUnits/SpecNormUnit.py
ASTRA/DataUnits/__init__.py
ASTRA/Instruments/CARMENES.py
ASTRA/Instruments/CustomFits.py
ASTRA/Instruments/ESO_PIPELINE.py
ASTRA/Instruments/ESPRESSO.py
ASTRA/Instruments/HARPS.py
ASTRA/Instruments/MAROONX.py
ASTRA/Instruments/SimulatedSpirou.py
ASTRA/Instruments/__init__.py
ASTRA/ModelParameters/Model.py
ASTRA/ModelParameters/Parameter.py
ASTRA/ModelParameters/__init__.py
ASTRA/Quality_Control/__init__.py
ASTRA/Quality_Control/activity_indicators.py
ASTRA/Quality_Control/ensure_value_in_limits.py
ASTRA/base_models/Frame.py
ASTRA/base_models/TemplateFramework.py
ASTRA/base_models/Template_Model.py
ASTRA/base_models/UnitModel.py
ASTRA/base_models/__init__.py
ASTRA/data_objects/DataClass.py
ASTRA/data_objects/MetaData.py
ASTRA/data_objects/Target.py
ASTRA/data_objects/__init__.py
ASTRA/internals/__init__.py
ASTRA/internals/cache.py
ASTRA/internals/db_tables.py
ASTRA/resources/__init__.py
ASTRA/resources/header_file.json
ASTRA/resources/internalSBART.db
ASTRA/resources/atmosphere_profiles/C-2.5+37.2D2021-08-29T03.gdas
ASTRA/resources/atmosphere_profiles/C-2.5+37.2D2021-09-09T03.gdas
ASTRA/resources/atmosphere_profiles/C-70.4-24.6D2019-05-05T21.gdas
ASTRA/resources/atmosphere_profiles/C-70.4-24.6D2019-06-10T21.gdas
ASTRA/resources/atmosphere_profiles/C-70.4-24.6D2019-07-03T00.gdas
ASTRA/resources/atmosphere_profiles/C-70.4-24.6D2019-11-30T03.gdas
ASTRA/resources/atmosphere_profiles/C-70.4-24.6D2020-12-01T00.gdas
ASTRA/resources/atmosphere_profiles/C-70.4-24.6D2020-12-05T00.gdas
ASTRA/resources/atmosphere_profiles/C-70.7-29.3D2023-08-12T00.gdas
ASTRA/resources/atmosphere_profiles/ESPRESSO_atmosphere_profile.txt
ASTRA/resources/atmosphere_profiles/ESPRESSO_gdas_profiles_C-70.4-24.6.tar.gz
ASTRA/resources/atmosphere_profiles/HARPS_atmosphere_profile.txt
astra_spectra-1.2.5.dist-info/licenses/LICENSE
astra_spectra-1.2.5.dist-info/METADATA
astra_spectra-1.2.5.dist-info/WHEEL
astra_spectra-1.2.5.dist-info/top_level.txt
astra_spectra-1.2.5.dist-info/RECORD
