Metadata-Version: 2.4
Name: ASTRA-spectra
Version: 1.2.5
Summary: Interface to open stellar spectra and construct stellar and telluric models
Requires-Python: <=3.12.8,>=3.11
License-File: LICENSE
Requires-Dist: astropy>=7.0.1
Requires-Dist: astroquery>=0.4.10
Requires-Dist: h5py>=3.13.0
Requires-Dist: loguru>=0.7.3
Requires-Dist: matplotlib>=3.10.1
Requires-Dist: numpy<2.0.0,>=1.23.2
Requires-Dist: pandas>=2.2.3
Requires-Dist: scipy>=1.15.2
Requires-Dist: sqlalchemy>=2.0.40
Requires-Dist: sqlalchemy-utils>=0.41.2
Requires-Dist: tables>=3.10.2
Requires-Dist: tabletexifier>=0.3.4
Requires-Dist: ujson>=5.10.0
Dynamic: license-file
